{
    "title": "{{count:quadros;legend=Propriedades de _Measurement_.}}",
    "fields": [
        {
            "type": "string",
            "name": "Nome"
        },
        {
            "type": "string",
            "name": "Exigência"
        },
        {
            "type": "string",
            "name": "Descrição"
        }
    ],
    "data": [
        ["Nome", "Exigência", "Descrição"],
        ["id", "opcional", ""],
        ["type", "obrigatório", "DEVE ser _AttributeAssignment_"],
        ["_label", "recomendado", ""],
        ["classified_as", "recomendado", ""],
        ["carried_out_by", "recomendado", ""],
        ["timespan", "opcional", ""],
        ["referred_to_by", "opcional", ""]
    ],
    "note": {
        "label": "Fonte",
        "content": "Elaborado pelo autor. Metadados utilizados no objeto _Measurements_ do Linked Art (2021)."
    }
}
